[
  {
    "name": "248deluxewoodenedition",
    "image": "http://youxistudio.com/img-new/248deluxewoodenedition.jpg",
    "link": "http://youxistudio.com",
    "type": "newgame"
  },
  {
    "name": "3dfootballmania",
    "image": "http://youxistudio.com/img-new/3dfootballmania.jpg",
    "link": "http://youxistudio.com",
    "type": "newgame"
  },
  {
    "name": "4inrowmania",
    "image": "http://youxistudio.com/img-new/4inrowmania.jpg",
    "link": "http://youxistudio.com",
    "type": "newgame"
  },
  {
    "name": "addictionmini",
    "image": "http://youxistudio.com/img-new/addictionmini.jpg",
    "link": "http://youxistudio.com",
    "type": "newgame"
  },
  {
    "name": "armoredassaultstrike",
    "image": "http://youxistudio.com/img-new/armoredassaultstrike.jpg",
    "link": "http://youxistudio.com",
    "type": "newgame"
  },
  {
    "name": "backyardzombiedefense",
    "image": "http://youxistudio.com/img-new/backyardzombiedefense.jpg",
    "link": "http://youxistudio.com",
    "type": "newgame"
  },
  {
    "name": "carromchallenges",
    "image": "http://youxistudio.com/img-new/carromchallenges.jpg",
    "link": "http://youxistudio.com",
    "type": "newgame"
  },
  {
    "name": "climbman",
    "image": "http://youxistudio.com/img-new/climbman.jpg",
    "link": "http://youxistudio.com",
    "type": "newgame"
  },
  {
    "name": "colorjump",
    "image": "http://youxistudio.com/img-new/colorjump.jpg",
    "link": "http://youxistudio.com",
    "type": "newgame"
  },
  {
    "name": "colorpin",
    "image": "http://youxistudio.com/img-new/colorpin.jpg",
    "link": "http://youxistudio.com",
    "type": "newgame"
  },
  {
    "name": "cookingmania",
    "image": "http://youxistudio.com/img-new/cookingmania.jpg",
    "link": "http://youxistudio.com",
    "type": "newgame"
  },
  {
    "name": "dalgonagame",
    "image": "http://youxistudio.com/img-new/dalgonagame.jpg",
    "link": "http://youxistudio.com",
    "type": "newgame"
  },
  {
    "name": "differencesfindquest",
    "image": "http://youxistudio.com/img-new/differencesfindquest.jpg",
    "link": "http://youxistudio.com",
    "type": "newgame"
  },
  {
    "name": "farming10x10",
    "image": "http://youxistudio.com/img-new/farming10x10.jpg",
    "link": "http://youxistudio.com",
    "type": "newgame"
  },
  {
    "name": "flip'nflapkitchenrace",
    "image": "http://youxistudio.com/img-new/flip'nflapkitchenrace.jpg",
    "link": "http://youxistudio.com",
    "type": "newgame"
  },
  {
    "name": "foosballcupworld",
    "image": "http://youxistudio.com/img-new/foosballcupworld.jpg",
    "link": "http://youxistudio.com",
    "type": "newgame"
  },
  {
    "name": "fruitslotmachine",
    "image": "http://youxistudio.com/img-new/fruitslotmachine.jpg",
    "link": "http://youxistudio.com",
    "type": "newgame"
  },
  {
    "name": "futoshiki",
    "image": "http://youxistudio.com/img-new/futoshiki.jpg",
    "link": "http://youxistudio.com",
    "type": "newgame"
  },
  {
    "name": "ghostproracing",
    "image": "http://youxistudio.com/img-new/ghostproracing.jpg",
    "link": "http://youxistudio.com",
    "type": "newgame"
  },
  {
    "name": "giantrush",
    "image": "http://youxistudio.com/img-new/giantrush.jpg",
    "link": "http://youxistudio.com",
    "type": "newgame"
  },
  {
    "name": "golfandfriends",
    "image": "http://youxistudio.com/img-new/golfandfriends.jpg",
    "link": "http://youxistudio.com",
    "type": "newgame"
  },
  {
    "name": "golforbit",
    "image": "http://youxistudio.com/img-new/golforbit.jpg",
    "link": "http://youxistudio.com",
    "type": "newgame"
  },
  {
    "name": "grannyhero",
    "image": "http://youxistudio.com/img-new/grannyhero.jpg",
    "link": "http://youxistudio.com",
    "type": "newgame"
  },
  {
    "name": "helikesthedarkness",
    "image": "http://youxistudio.com/img-new/helikesthedarkness.jpg",
    "link": "http://youxistudio.com",
    "type": "newgame"
  },
  {
    "name": "hexamind",
    "image": "http://youxistudio.com/img-new/hexamind.jpg",
    "link": "http://youxistudio.com",
    "type": "newgame"
  },
  {
    "name": "jewelduel",
    "image": "http://youxistudio.com/img-new/jewelduel.jpg",
    "link": "http://youxistudio.com",
    "type": "newgame"
  },
  {
    "name": "mergehaven",
    "image": "http://youxistudio.com/img-new/mergehaven.jpg",
    "link": "http://youxistudio.com",
    "type": "newgame"
  },
  {
    "name": "messontheranch",
    "image": "http://youxistudio.com/img-new/messontheranch.jpg",
    "link": "http://youxistudio.com",
    "type": "newgame"
  },
  {
    "name": "minigolfworld",
    "image": "http://youxistudio.com/img-new/minigolfworld.jpg",
    "link": "http://youxistudio.com",
    "type": "newgame"
  },
  {
    "name": "penaltyshowdown",
    "image": "http://youxistudio.com/img-new/penaltyshowdown.jpg",
    "link": "http://youxistudio.com",
    "type": "newgame"
  },
  {
    "name": "pickalock",
    "image": "http://youxistudio.com/img-new/pickalock.jpg",
    "link": "http://youxistudio.com",
    "type": "newgame"
  },
  {
    "name": "secretagent",
    "image": "http://youxistudio.com/img-new/secretagent.jpg",
    "link": "http://youxistudio.com",
    "type": "newgame"
  },
  {
    "name": "solitaire0-21",
    "image": "http://youxistudio.com/img-new/solitaire0-21.jpg",
    "link": "http://youxistudio.com",
    "type": "newgame"
  },
  {
    "name": "sortworks",
    "image": "http://youxistudio.com/img-new/sortworks.jpg",
    "link": "http://youxistudio.com",
    "type": "newgame"
  },
  {
    "name": "subwayjumper",
    "image": "http://youxistudio.com/img-new/subwayjumper.jpg",
    "link": "http://youxistudio.com",
    "type": "newgame"
  },
  {
    "name": "survivorlegends",
    "image": "http://youxistudio.com/img-new/survivorlegends.jpg",
    "link": "http://youxistudio.com",
    "type": "newgame"
  },
  {
    "name": "thiefpuzzle",
    "image": "http://youxistudio.com/img-new/thiefpuzzle.jpg",
    "link": "http://youxistudio.com",
    "type": "newgame"
  },
  {
    "name": "tinyfootballcup",
    "image": "http://youxistudio.com/img-new/tinyfootballcup.jpg",
    "link": "http://youxistudio.com",
    "type": "newgame"
  },
  {
    "name": "tractormania",
    "image": "http://youxistudio.com/img-new/tractormania.jpg",
    "link": "http://youxistudio.com",
    "type": "newgame"
  },
  {
    "name": "trainminer",
    "image": "http://youxistudio.com/img-new/trainminer.jpg",
    "link": "http://youxistudio.com",
    "type": "newgame"
  },
  {
    "name": "westernsniper",
    "image": "http://youxistudio.com/img-new/westernsniper.jpg",
    "link": "http://youxistudio.com",
    "type": "newgame"
  },
  {
    "name": "wordler",
    "image": "http://youxistudio.com/img-new/wordler.jpg",
    "link": "http://youxistudio.com",
    "type": "newgame"
  },
  {
    "name": "wordschallenge",
    "image": "http://youxistudio.com/img-new/wordschallenge.jpg",
    "link": "http://youxistudio.com",
    "type": "newgame"
  },
  {
    "name": "zombiegun",
    "image": "http://youxistudio.com/img-new/zombiegun.jpg",
    "link": "http://youxistudio.com",
    "type": "newgame"
  }
]